odoo/addons/project_task_milestone/README.rst
odoo/addons/project_task_milestone/__init__.py
odoo/addons/project_task_milestone/__manifest__.py
odoo/addons/project_task_milestone/i18n/it.po
odoo/addons/project_task_milestone/i18n/project_task_milestone.pot
odoo/addons/project_task_milestone/models/__init__.py
odoo/addons/project_task_milestone/models/project_milestone.py
odoo/addons/project_task_milestone/models/project_task.py
odoo/addons/project_task_milestone/readme/CONTRIBUTORS.rst
odoo/addons/project_task_milestone/readme/CREDITS.rst
odoo/addons/project_task_milestone/readme/DESCRIPTION.rst
odoo/addons/project_task_milestone/static/description/icon.png
odoo/addons/project_task_milestone/static/description/index.html
odoo/addons/project_task_milestone/tests/__init__.py
odoo/addons/project_task_milestone/tests/test_project_milestone.py
odoo/addons/project_task_milestone/views/project_task.xml
odoo_addon_project_task_milestone-15.0.1.0.0.10.dist-info/METADATA
odoo_addon_project_task_milestone-15.0.1.0.0.10.dist-info/WHEEL
odoo_addon_project_task_milestone-15.0.1.0.0.10.dist-info/top_level.txt
odoo_addon_project_task_milestone-15.0.1.0.0.10.dist-info/RECORD
